{"cameraMode":{"drawMode":0,"name":"Shaded","section":"Shading Mode"},"sceneLighting":true,"audioPlay":false,"sceneViewState":{"m_AlwaysRefresh":false,"showFog":true,"showSkybox":true,"showFlares":true,"showImageEffects":true,"showParticleSystems":true,"showVisualEffectGraphs":true,"m_FxEnabled":true},"in2DMode":false,"pivot":{"x":-10.44058895111084,"y":-11.631874084472657,"z":4.414689540863037},"rotation":{"x":0.361336350440979,"y":-0.5264800786972046,"z":0.2633790969848633,"w":0.7232611775398254},"size":11.566449165344239,"orthographic":false}